[{"district": "Zuffenhausen", "file": "data/districts/zuffenhausen.geojson", "cells": 785}, {"district": "Süd", "file": "data/districts/sued.geojson", "cells": 648}, {"district": "West", "file": "data/districts/west.geojson", "cells": 978}, {"district": "Bad Cannstatt", "file": "data/districts/bad-cannstatt.geojson", "cells": 1038}, {"district": "Mitte", "file": "data/districts/mitte.geojson", "cells": 262}, {"district": "Untertürkheim", "file": "data/districts/untertuerkheim.geojson", "cells": 423}, {"district": "Feuerbach", "file": "data/districts/feuerbach.geojson", "cells": 729}, {"district": "Vaihingen", "file": "data/districts/vaihingen.geojson", "cells": 1100}, {"district": "Ost", "file": "data/districts/ost.geojson", "cells": 610}, {"district": "Degerloch", "file": "data/districts/degerloch.geojson", "cells": 550}]