[{"district":"Bad Cannstatt","cells":282,"interpolated_cells":1,"lst_06":35.128,"lst_18":37.471,"uhi_06":5.67,"uhi_18":4.197,"ndvi_06":0.222,"ndvi_18":0.231,"heat_06":61.557,"heat_18":65.95,"lst_change":2.3,"uhi_change":-1.5,"ndvi_change":0.009},{"district":"Degerloch","cells":152,"interpolated_cells":0,"lst_06":29.252,"lst_18":32.687,"uhi_06":-0.205,"uhi_18":-0.591,"ndvi_06":0.321,"ndvi_18":0.33,"heat_06":27.645,"heat_18":37.605,"lst_change":3.4,"uhi_change":-0.4,"ndvi_change":0.009},{"district":"Feuerbach","cells":209,"interpolated_cells":8,"lst_06":31.411,"lst_18":34.487,"uhi_06":1.951,"uhi_18":1.218,"ndvi_06":0.293,"ndvi_18":0.304,"heat_06":39.297,"heat_18":47.344,"lst_change":3.1,"uhi_change":-0.7,"ndvi_change":0.011},{"district":"Mitte","cells":66,"interpolated_cells":0,"lst_06":37.264,"lst_18":39.33,"uhi_06":7.814,"uhi_18":6.059,"ndvi_06":0.149,"ndvi_18":0.147,"heat_06":75.333,"heat_18":78.939,"lst_change":2.1,"uhi_change":-1.8,"ndvi_change":-0.002},{"district":"Ost","cells":173,"interpolated_cells":0,"lst_06":32.105,"lst_18":35.018,"uhi_06":2.652,"uhi_18":1.747,"ndvi_06":0.266,"ndvi_18":0.274,"heat_06":44.376,"heat_18":51.728,"lst_change":2.9,"uhi_change":-0.9,"ndvi_change":0.008},{"district":"Süd","cells":159,"interpolated_cells":1,"lst_06":30.179,"lst_18":33.294,"uhi_06":0.725,"uhi_18":0.021,"ndvi_06":0.3,"ndvi_18":0.31,"heat_06":33.164,"heat_18":41.478,"lst_change":3.1,"uhi_change":-0.7,"ndvi_change":0.01},{"district":"Untertürkheim","cells":120,"interpolated_cells":0,"lst_06":33.996,"lst_18":36.464,"uhi_06":4.546,"uhi_18":3.202,"ndvi_06":0.241,"ndvi_18":0.253,"heat_06":54.25,"heat_18":59.217,"lst_change":2.5,"uhi_change":-1.3,"ndvi_change":0.012},{"district":"Vaihingen","cells":357,"interpolated_cells":45,"lst_06":29.615,"lst_18":32.355,"uhi_06":0.158,"uhi_18":-0.915,"ndvi_06":0.307,"ndvi_18":0.317,"heat_06":30.202,"heat_18":36.555,"lst_change":2.7,"uhi_change":-1.1,"ndvi_change":0.01},{"district":"West","cells":330,"interpolated_cells":49,"lst_06":27.506,"lst_18":31.061,"uhi_06":-1.949,"uhi_18":-2.212,"ndvi_06":0.337,"ndvi_18":0.352,"heat_06":18.833,"heat_18":28.573,"lst_change":3.6,"uhi_change":-0.3,"ndvi_change":0.015},{"district":"Zuffenhausen","cells":222,"interpolated_cells":4,"lst_06":33.443,"lst_18":36.299,"uhi_06":3.986,"uhi_18":3.023,"ndvi_06":0.263,"ndvi_18":0.274,"heat_06":51.351,"heat_18":58.306,"lst_change":2.9,"uhi_change":-1.0,"ndvi_change":0.011}]